README.md
setup.py
stochastic_distribution/Binomialdistribution.py
stochastic_distribution/Gaussiandistribution.py
stochastic_distribution/Generaldistribution.py
stochastic_distribution/__init__.py
stochastic_distribution.egg-info/PKG-INFO
stochastic_distribution.egg-info/SOURCES.txt
stochastic_distribution.egg-info/dependency_links.txt
stochastic_distribution.egg-info/not-zip-safe
stochastic_distribution.egg-info/top_level.txt