Metadata-Version: 2.1
Name: stochastic-distribution
Version: 0.2
Summary: Gaussian and Binomial distributions
Home-page: UNKNOWN
Author: Robert Csillag
Author-email: csillagrobert95@gmail.com
License: UNKNOWN
Platform: UNKNOWN
